LICENSE
MANIFEST.in
README
setup.py
src/sleipnir/__init__.py
src/sleipnir.testing.egg-info/PKG-INFO
src/sleipnir.testing.egg-info/SOURCES.txt
src/sleipnir.testing.egg-info/dependency_links.txt
src/sleipnir.testing.egg-info/namespace_packages.txt
src/sleipnir.testing.egg-info/not-zip-safe
src/sleipnir.testing.egg-info/top_level.txt
src/sleipnir/testing/__init__.py
src/sleipnir/testing/components.py
src/sleipnir/testing/constants.py
src/sleipnir/testing/test.py
src/sleipnir/testing/data/README
src/sleipnir/testing/data/__init__.py
src/sleipnir/testing/data/interfaces/__init__.py
src/sleipnir/testing/data/interfaces/hello.py
src/sleipnir/testing/data/interfaces/salut.py
src/sleipnir/testing/data/plugins/README
src/sleipnir/testing/data/plugins/eggs/fail/README
src/sleipnir/testing/data/plugins/eggs/fail/__init__.py
src/sleipnir/testing/data/plugins/eggs/fail/setup.py
src/sleipnir/testing/data/plugins/eggs/hello/README
src/sleipnir/testing/data/plugins/eggs/hello/setup.py
src/sleipnir/testing/data/plugins/eggs/hello/hello_plugin/__init__.py
src/sleipnir/testing/data/plugins/eggs/hello/hello_plugin/hello_world.py
src/sleipnir/testing/data/plugins/python/salut_world.py
src/sleipnir/testing/data/tsplib/00.dct
src/sleipnir/testing/data/tsplib/01.dct
src/sleipnir/testing/data/tsplib/02.dct
src/sleipnir/testing/data/tsplib/03.dct
src/sleipnir/testing/data/tsplib/04.dct
src/sleipnir/testing/data/tsplib/05.dct
src/sleipnir/testing/data/tsplib/06.dct
src/sleipnir/testing/data/tsplib/README
src/sleipnir/testing/data/tsplib/a280.tsp